scratchconnect/CloudConnection.py
scratchconnect/Exceptions.py
scratchconnect/Forum.py
scratchconnect/Project.py
scratchconnect/ScratchConnect.py
scratchconnect/Studio.py
scratchconnect/TurbowarpCloudConnection.py
scratchconnect/User.py
scratchconnect/UserCommon.py
scratchconnect/Warnings.py
scratchconnect/__init__.py
scratchconnect/scCloudEvents.py
scratchconnect/scCloudRequests.py
scratchconnect/scCloudStorage.py
scratchconnect/scEncoder.py
scratchconnect/scImage.py
scratchconnect/scOnlineIDE.py
scratchconnect/scScratchTerminal.py
scratchconnect-5.0.dist-info/LICENSE
scratchconnect-5.0.dist-info/METADATA
scratchconnect-5.0.dist-info/WHEEL
scratchconnect-5.0.dist-info/top_level.txt
scratchconnect-5.0.dist-info/RECORD
