Metadata-Version: 2.1
Name: scratchconnect
Version: 5.0
Summary: Python Library to connect Scratch API and much more. This library can show the statistics of Users, Projects, Studios, Forums and also connect and set cloud variables of a project!
Home-page: https://github.com/Sid72020123/scratchconnect/
Author: Siddhesh Chavan
Author-email: siddheshchavan2020@gmail.com
License: MIT
Keywords: connect scratch,scratch api,api,scratch,bot,scratch bot,scratch cloud,scratch cloud variables,scratch data,scratch stats,cloud requests,fast cloud requests
Classifier: Development Status :: 5 - Production/Stable
Classifier: Intended Audience :: Education
Classifier: Operating System :: OS Independent
Classifier: License :: OSI Approved :: MIT License
Classifier: Programming Language :: Python :: 3
License-File: LICENSE
Requires-Dist: requests
Requires-Dist: websocket-client
Requires-Dist: Pillow
Provides-Extra: terminal
Requires-Dist: scScratchTerminal ; extra == 'terminal'
